{
	"summary": {
		"locale": {
			"country": "US",
			"language": "en"
		},
		"API-Version": "v1",
		"API-Name": "Catalogue/Attribute/Values"
	},
	"catalogueAttributeValue": [{
		"ID": "NOT APPLICABLE",
		"description": "NOT APPLICABLE"
	}, {
		"ID": "Jun 2015",
		"description": "Jun 2015"
	}, {
		"ID": "May 2015",
		"description": "May 2015"
	}, {
		"ID": "Apr 2015",
		"description": "Apr 2015"
	}, {
		"ID": "Mar 2015",
		"description": "Mar 2015"
	}, {
		"ID": "Feb 2015",
		"description": "Feb 2015"
	}, {
		"ID": "Jan 2015",
		"description": "Jan 2015"
	}, {
		"ID": "Dec 2014",
		"description": "Dec 2014"
	}, {
		"ID": "Nov 2014",
		"description": "Nov 2014"
	}, {
		"ID": "Oct 2014",
		"description": "Oct 2014"
	}, {
		"ID": "Sep 2014",
		"description": "Sep 2014"
	}, {
		"ID": "Aug 2014",
		"description": "Aug 2014"
	}, {
		"ID": "Jul 2014",
		"description": "Jul 2014"
	}, {
		"ID": "Jun 2014",
		"description": "Jun 2014"
	}, {
		"ID": "May 2014",
		"description": "May 2014"
	}, {
		"ID": "Apr 2014",
		"description": "Apr 2014"
	}, {
		"ID": "Mar 2014",
		"description": "Mar 2014"
	}, {
		"ID": "Feb 2014",
		"description": "Feb 2014"
	}, {
		"ID": "Jan 2014",
		"description": "Jan 2014"
	}, {
		"ID": "Dec 2013",
		"description": "Dec 2013"
	}, {
		"ID": "Nov 2013",
		"description": "Nov 2013"
	}, {
		"ID": "Oct 2013",
		"description": "Oct 2013"
	}, {
		"ID": "Sep 2013",
		"description": "Sep 2013"
	}, {
		"ID": "Aug 2013",
		"description": "Aug 2013"
	}, {
		"ID": "Jul 2013",
		"description": "Jul 2013"
	}, {
		"ID": "Jun 2013",
		"description": "Jun 2013"
	}, {
		"ID": "May 2013",
		"description": "May 2013"
	}, {
		"ID": "Apr 2013",
		"description": "Apr 2013"
	}, {
		"ID": "Mar 2013",
		"description": "Mar 2013"
	}, {
		"ID": "Feb 2013",
		"description": "Feb 2013"
	}, {
		"ID": "Jan 2013",
		"description": "Jan 2013"
	}, {
		"ID": "Dec 2012",
		"description": "Dec 2012"
	}, {
		"ID": "Nov 2012",
		"description": "Nov 2012"
	}, {
		"ID": "Oct 2012",
		"description": "Oct 2012"
	}, {
		"ID": "Sep 2012",
		"description": "Sep 2012"
	}, {
		"ID": "Aug 2012",
		"description": "Aug 2012"
	}, {
		"ID": "Jul 2012",
		"description": "Jul 2012"
	}, {
		"ID": "Jun 2012",
		"description": "Jun 2012"
	}, {
		"ID": "May 2012",
		"description": "May 2012"
	}, {
		"ID": "Apr 2012",
		"description": "Apr 2012"
	}, {
		"ID": "Mar 2012",
		"description": "Mar 2012"
	}, {
		"ID": "Feb 2012",
		"description": "Feb 2012"
	}, {
		"ID": "Jan 2012",
		"description": "Jan 2012"
	}, {
		"ID": "Dec 2011",
		"description": "Dec 2011"
	}, {
		"ID": "Nov 2011",
		"description": "Nov 2011"
	}, {
		"ID": "Oct 2011",
		"description": "Oct 2011"
	}, {
		"ID": "Sep 2011",
		"description": "Sep 2011"
	}, {
		"ID": "Aug 2011",
		"description": "Aug 2011"
	}, {
		"ID": "Jul 2011",
		"description": "Jul 2011"
	}, {
		"ID": "Jun 2011",
		"description": "Jun 2011"
	}, {
		"ID": "May 2011",
		"description": "May 2011"
	}, {
		"ID": "Apr 2011",
		"description": "Apr 2011"
	}, {
		"ID": "Mar 2011",
		"description": "Mar 2011"
	}, {
		"ID": "Feb 2011",
		"description": "Feb 2011"
	}, {
		"ID": "Jan 2011",
		"description": "Jan 2011"
	}, {
		"ID": "Dec 2010",
		"description": "Dec 2010"
	}, {
		"ID": "Nov 2010",
		"description": "Nov 2010"
	}, {
		"ID": "Oct 2010",
		"description": "Oct 2010"
	}, {
		"ID": "Sep 2010",
		"description": "Sep 2010"
	}, {
		"ID": "Aug 2010",
		"description": "Aug 2010"
	}, {
		"ID": "Jul 2010",
		"description": "Jul 2010"
	}, {
		"ID": "Jun 2010",
		"description": "Jun 2010"
	}]
}